<?xml version="1.0" encoding="utf-8"?>
<!DOCTYPE hibernate-mapping PUBLIC "-//Hibernate/Hibernate Mapping DTD 3.0//EN"
"http://hibernate.sourceforge.net/hibernate-mapping-3.0.dtd">
<!-- 
    Mapping file autogenerated by MyEclipse Persistence Tools
-->
<hibernate-mapping>
    <class name="org.translate.min.entity.MyTranslate" table="mytranslate" catalog="translationbyfee">
        <composite-id name="id" class="org.translate.min.entity.MyTranslateId">
            <key-property name="finishedNewsId" type="integer">
                <column name="finishedNewsId" />
            </key-property>
            <key-property name="originNewsId" type="integer">
                <column name="originNewsId" />
            </key-property>
            <key-property name="translatorUserName" type="string">
                <column name="translatorUserName" length="20" />
            </key-property>
            <key-property name="originLanguage" type="string">
                <column name="originLanguage" length="20" />
            </key-property>
            <key-property name="objectLanguage" type="string">
                <column name="objectLanguage" length="20" />
            </key-property>
            <key-property name="finishedTitle" type="string">
                <column name="finishedTitle" />
            </key-property>
            <key-property name="finishedContent" type="string">
                <column name="finishedContent" length="65535" />
            </key-property>
            <key-property name="finishedDate" type="date">
                <column name="finishedDate" length="10" />
            </key-property>
        </composite-id>
    </class>
</hibernate-mapping>
